final_test05/__init__.py
final_test05/adaboost.py
final_test05/grad_boost.py
final_test05/knn.py
final_test05/logistic.py
final_test05/mlp.py
final_test05/my_func.py
final_test05/perceptron.py
final_test05/random_forest.py
final_test05/sgd.py
final_test05/support_vector.py
final_test05/visualize.py
final_test05/xgboost.py
final_test_09-0.1.0.dist-info/LICENSE
final_test_09-0.1.0.dist-info/METADATA
final_test_09-0.1.0.dist-info/WHEEL
final_test_09-0.1.0.dist-info/top_level.txt
final_test_09-0.1.0.dist-info/RECORD
